certbot_dns_cdmon/__init__.py
certbot_dns_cdmon/dns_cdmon.py
certbot_dns_cdmon-0.4.1.dist-info/METADATA
certbot_dns_cdmon-0.4.1.dist-info/WHEEL
certbot_dns_cdmon-0.4.1.dist-info/entry_points.txt
certbot_dns_cdmon-0.4.1.dist-info/top_level.txt
certbot_dns_cdmon-0.4.1.dist-info/RECORD
